scaffoldmaker/__init__.py
scaffoldmaker/scaffoldpackage.py
scaffoldmaker/scaffolds.py
scaffoldmaker/annotation/__init__.py
scaffoldmaker/annotation/annotation_utils.py
scaffoldmaker/annotation/annotationgroup.py
scaffoldmaker/annotation/bladder_terms.py
scaffoldmaker/annotation/body_terms.py
scaffoldmaker/annotation/brainstem_terms.py
scaffoldmaker/annotation/cecum_terms.py
scaffoldmaker/annotation/colon_terms.py
scaffoldmaker/annotation/esophagus_terms.py
scaffoldmaker/annotation/heart_terms.py
scaffoldmaker/annotation/lung_terms.py
scaffoldmaker/annotation/muscle_terms.py
scaffoldmaker/annotation/nerve_terms.py
scaffoldmaker/annotation/smallintestine_terms.py
scaffoldmaker/annotation/spinal_nerve_terms.py
scaffoldmaker/annotation/stellate_terms.py
scaffoldmaker/annotation/stomach_terms.py
scaffoldmaker/annotation/trigeminal_nerve_terms.py
scaffoldmaker/annotation/uterus_terms.py
scaffoldmaker/annotation/vagus_terms.py
scaffoldmaker/meshtypes/__init__.py
scaffoldmaker/meshtypes/meshtype_1d_bifurcationtree1.py
scaffoldmaker/meshtypes/meshtype_1d_network_layout1.py
scaffoldmaker/meshtypes/meshtype_1d_path1.py
scaffoldmaker/meshtypes/meshtype_2d_plate1.py
scaffoldmaker/meshtypes/meshtype_2d_platehole1.py
scaffoldmaker/meshtypes/meshtype_2d_sphere1.py
scaffoldmaker/meshtypes/meshtype_2d_tube1.py
scaffoldmaker/meshtypes/meshtype_2d_tubenetwork1.py
scaffoldmaker/meshtypes/meshtype_3d_bladder1.py
scaffoldmaker/meshtypes/meshtype_3d_bladderurethra1.py
scaffoldmaker/meshtypes/meshtype_3d_bone1.py
scaffoldmaker/meshtypes/meshtype_3d_box1.py
scaffoldmaker/meshtypes/meshtype_3d_boxhole1.py
scaffoldmaker/meshtypes/meshtype_3d_boxnetwork1.py
scaffoldmaker/meshtypes/meshtype_3d_brainstem.py
scaffoldmaker/meshtypes/meshtype_3d_cecum1.py
scaffoldmaker/meshtypes/meshtype_3d_colon1.py
scaffoldmaker/meshtypes/meshtype_3d_colonsegment1.py
scaffoldmaker/meshtypes/meshtype_3d_ellipsoid1.py
scaffoldmaker/meshtypes/meshtype_3d_esophagus1.py
scaffoldmaker-0.19.1.dist-info/licenses/LICENSE
scaffoldmaker-0.19.1.dist-info/METADATA
scaffoldmaker-0.19.1.dist-info/WHEEL
scaffoldmaker-0.19.1.dist-info/top_level.txt
scaffoldmaker-0.19.1.dist-info/RECORD
