Metadata-Version: 2.4
Name: scaffoldmaker
Version: 0.19.1
Summary: Python client for generating anatomical scaffolds using Zinc.
Author-email: Richard Christie <r.christie@auckland.ac.nz>
License: 
Keywords: Medical,Physiology,Anatomical,Mesh,Finite Element,SPARC
Classifier: Programming Language :: Python :: 3
Classifier: License :: OSI Approved :: Apache Software License
Classifier: Operating System :: OS Independent
Requires-Python: >=3.8
License-File: LICENSE
Requires-Dist: cmlibs.maths>=0.7.1
Requires-Dist: cmlibs.utils>=0.12.5
Requires-Dist: cmlibs.zinc>=4.2.1
Requires-Dist: fieldfitter>=0.6.0
Requires-Dist: scaffoldfitter>=0.11.1
Requires-Dist: scipy
Requires-Dist: numpy
Dynamic: license-file
